open_sdk_py/__init__.py
open_sdk_py/constants.py
open_sdk_py/encrypt.py
open_sdk_py/exception.py
open_sdk_py/result.py
open_sdk_py/sdk_client.py
open_sdk_py/resources/RSA-PublicKey.pem
open_sdk_py/resources/SM2-PublicKey.pem
tests/__init__.py
tests/test_client.py
open_sdk_py-2.1.1.dist-info/LICENSE
open_sdk_py-2.1.1.dist-info/METADATA
open_sdk_py-2.1.1.dist-info/WHEEL
open_sdk_py-2.1.1.dist-info/top_level.txt
open_sdk_py-2.1.1.dist-info/RECORD
