Metadata-Version: 2.1
Name: open-sdk-py
Version: 2.1.1
Summary: 云枢开放服务平台集成SDK工具（Python版）
Author: CynicalHeart
Author-email: wutianyu@yljr.com
License: MIT
Classifier: Programming Language :: Python :: 3
Classifier: License :: OSI Approved :: MIT License
Classifier: Operating System :: OS Independent
Requires-Python: >=3.7
License-File: LICENSE
Requires-Dist: requests
Requires-Dist: cryptography
Requires-Dist: gmssl
Requires-Dist: certifi
